TicTacToe3/__errors__.py
TicTacToe3/__functions__.py
TicTacToe3/__init__.py
TicTacToe3-0.1.1.dist-info/LICENSE
TicTacToe3-0.1.1.dist-info/METADATA
TicTacToe3-0.1.1.dist-info/WHEEL
TicTacToe3-0.1.1.dist-info/top_level.txt
TicTacToe3-0.1.1.dist-info/RECORD
