Metadata-Version: 2.1
Name: TicTacToe3
Version: 0.1.1
Summary: A game of Tic Tac Toe, that you may RARELY WIN
Home-page: UNKNOWN
Author: Programmin-in-Python (MK)
Author-email: <kalanithi6014@gmail.com>
License: UNKNOWN
Project-URL: GitHub, https://github.com/Programmin-in-Python/TicTacToe-cli
Project-URL: Release Notes, https://github.com/Programmin-in-Python/TicTacToe-cli/releases/tag/v0.1.1
Project-URL: Home Page, https://github.com/Programmin-in-Python/TicTacToe-cli
Keywords: python3,Tic Tac Toe,Tic-Tac-Toe,tic tac toe,tic-tac-toe,tic-tac-toe-cli,probability
Platform: UNKNOWN
Classifier: Development Status :: 5 - Production/Stable
Classifier: Intended Audience :: Science/Research
Classifier: Intended Audience :: Education
Classifier: License :: OSI Approved :: MIT License
Classifier: Natural Language :: English
Classifier: Operating System :: Unix
Classifier: Operating System :: MacOS :: MacOS X
Classifier: Operating System :: Microsoft :: Windows
Classifier: Operating System :: OS Independent
Classifier: Programming Language :: Python :: 3 :: Only
Classifier: Programming Language :: Python :: 3
Classifier: Topic :: Education
Classifier: Topic :: Games/Entertainment :: Board Games
Classifier: Topic :: Games/Entertainment :: Puzzle Games
Classifier: Topic :: Scientific/Engineering :: Mathematics
Requires-Python: >=3
